Module2_Advanced_RTL_Design_and_CDC_and_RDC_Handling/FIFO_design_for_asynchronous_interfaces/async_fifo.v
module async_fifo(
	input wr_clk,rd_clk,
	input wr_rst,rd_rst,
	input wr_en,rd_en,
	input [7:0] wr_data,
	output reg [7:0] rd_data,
        output reg wr_full,rd_empty
);
reg [7:0] mem [0:7];
reg [2:0] wr_ptr=0,rd_ptr=0;

always@(posedge wr_clk or posedge wr_rst)begin
	if(wr_rst)
		wr_ptr<=0;
	else if(wr_en && !wr_full) begin
		mem[wr_ptr]<=wr_data;
		wr_ptr<=wr_ptr+1;
	end
end

always@(posedge rd_clk or posedge rd_rst)begin
	if(rd_rst)
		rd_ptr<=0;
	else if(rd_en && !rd_empty)begin
		rd_data<=mem[rd_ptr];
		rd_ptr<=rd_ptr+1;
	end
end
always @(*) begin
 wr_full = ((wr_ptr + 3'd1)  == rd_ptr);
 rd_empty = (wr_ptr == rd_ptr);
 end
endmodule

Module2_Advanced_RTL_Design_and_CDC_and_RDC_Handling/FIFO_design_for_asynchronous_interfaces/async_fifo_tb.v
module async_fifo_tb;
reg wr_clk = 0, rd_clk = 0;
 reg wr_rst = 1, rd_rst = 1;
 reg wr_en = 0, rd_en = 0;
 reg [7:0] wr_data = 8'd0;
 wire [7:0] rd_data;
 wire wr_full, rd_empty;

 always #5 wr_clk<=~wr_clk;
 always #7 rd_clk <= ~rd_clk;

async_fifo uut (
 .wr_clk(wr_clk), .rd_clk(rd_clk),
 .wr_rst(wr_rst), .rd_rst(rd_rst),
 .wr_en(wr_en), .rd_en(rd_en),
 .wr_data(wr_data), .rd_data(rd_data),
 .wr_full(wr_full), .rd_empty(rd_empty)
 );         

 initial begin
 $dumpfile("dump.vcd");
 $dumpvars();

 #10 wr_rst=0;#10 rd_rst=0;

 repeat (4) begin
	 @(posedge wr_clk);
	 wr_en=1;
	 wr_data=wr_data+1;
 end
 wr_en=0;
 #30
 repeat (4) begin
	 @(posedge rd_clk);
	 rd_en=1;
 end
 rd_en=0;
 #100 $finish;
 end
 endmodule

Module2_Advanced_RTL_Design_and_CDC_and_RDC_Handling/FIFO_design_for_asynchronous_interfaces/obj_dir/dump.vcd
$version Generated by VerilatedVcd $end
$timescale 1ps $end

 $scope module TOP $end
  $scope module async_fifo_tb $end
   $var wire  1 2 rd_clk $end
   $var wire  8 3 rd_data [7:0] $end
   $var wire  1 5 rd_empty $end
   $var wire  1 & rd_en $end
   $var wire  1 $ rd_rst $end
   $var wire  1 1 wr_clk $end
   $var wire  8 ' wr_data [7:0] $end
   $var wire  1 % wr_en $end
   $var wire  1 4 wr_full $end
   $var wire  1 # wr_rst $end
   $scope module uut $end
    $var wire  8 ( mem[0] [7:0] $end
    $var wire  8 ) mem[1] [7:0] $end
    $var wire  8 * mem[2] [7:0] $end
    $var wire  8 + mem[3] [7:0] $end
    $var wire  8 , mem[4] [7:0] $end
    $var wire  8 - mem[5] [7:0] $end
    $var wire  8 . mem[6] [7:0] $end
    $var wire  8 / mem[7] [7:0] $end
    $var wire  1 2 rd_clk $end
    $var wire  8 3 rd_data [7:0] $end
    $var wire  1 5 rd_empty $end
    $var wire  1 & rd_en $end
    $var wire  3 6 rd_ptr [2:0] $end
    $var wire  1 $ rd_rst $end
    $var wire  1 1 wr_clk $end
    $var wire  8 ' wr_data [7:0] $end
    $var wire  1 % wr_en $end
    $var wire  1 4 wr_full $end
    $var wire  3 0 wr_ptr [2:0] $end
    $var wire  1 # wr_rst $end
   $upscope $end
  $upscope $end
 $upscope $end
$enddefinitions $end


#0
1#
1$
0%
0&
b00000000 '
b00000000 (
b00000000 )
b00000000 *
b00000000 +
b00000000 ,
b00000000 -
b00000000 .
b00000000 /
b000 0
01
02
b00000000 3
04
15
b000 6
#5
11
#7
12
#10
0#
01
#14
02
#15
11
#20
0$
01
#21
12
#25
1%
b00000001 '
b00000001 (
b001 0
11
05
#28
02
#30
01
#35
b00000010 '
b00000010 )
b010 0
11
12
#40
01
#42
02
#45
b00000011 '
b00000011 *
b011 0
11
#49
12
#50
01
#55
0%
b00000100 '
11
#56
02
#60
01
#63
12
#65
11
#70
01
02
#75
11
#77
12
#80
01
#84
02
#85
11
#90
01
#91
1&
12
b00000001 3
b001 6
#95
11
#98
02
#100
01
#105
11
12
b00000010 3
b010 6
#110
01
#112
02
#115
11
#119
12
b00000011 3
15
b011 6
#120
01
#125
11
#126
02
#130
01
#133
0&
12
