Module1_RTL_Design_and_IP_Integration/mini_soc/mux.v
module mux(
	input [1:0] in1,
	input [1:0] in2,
	input sel,
	output [1:0] y);
assign y=sel?in1:in2;
endmodule

Module1_RTL_Design_and_IP_Integration/mini_soc/alu.v
module alu(
	input [1:0] a,
        input [1:0] b,
	input sel,
	output reg [1:0] result);
always @(*) begin
	case(sel)
		1'b0:result=a+b;
		1'b1:result=a-b;
		default:result=0;
	endcase
end
endmodule

Module1_RTL_Design_and_IP_Integration/mini_soc/counter.v
module counter(
	input clk,rst,
	output reg [3:0] count);
always @(posedge clk)begin
	if(rst)
		count<=0;
	else
		count<=count+1;
end
endmodule

Module1_RTL_Design_and_IP_Integration/mini_soc/mini_soc.v
module mini_soc(
	input clk,
	input rst,
	input mux_sel,
	input alu_sel,
	output [1:0] soc_output);
wire [3:0] count;
wire [1:0] alu_out;

counter dut(.clk(clk),.rst(rst),.count(count));
alu uut(.a(count[3:2]),.b(count[1:0]),.sel(alu_sel),.result(alu_out));
mux sut(.in1(count[3:2]),.in2(alu_out),.sel(mux_sel),.y(soc_output));
endmodule

Module1_RTL_Design_and_IP_Integration/mini_soc/mini_soc_tb.v
module mini_soc_tb;
reg clk,rst,alu_sel,mux_sel;
wire [1:0] soc_output;
mini_soc but(.clk(clk),.rst(rst),.alu_sel(alu_sel),.mux_sel(mux_sel),.soc_output(soc_output));
always #5 clk<=~clk;
initial begin
	$dumpfile("soc_dump.vcd");
	$dumpvars();

	#10 rst=0;
	#20 alu_sel=1;
	#30 mux_sel=0;
	#10 alu_sel=1;
	#20 mux_sel=0;
	#50 $finish;
end
endmodule

Module1_RTL_Design_and_IP_Integration/mini_soc/obj_dir/soc_dump.vcd
$version Generated by VerilatedVcd $end
$timescale 1ps $end

 $scope module TOP $end
  $scope module mini_soc_tb $end
   $var wire  1 ( alu_sel $end
   $var wire  1 & clk $end
   $var wire  1 ) mux_sel $end
   $var wire  1 ' rst $end
   $var wire  2 * soc_output [1:0] $end
   $scope module but $end
    $var wire  2 + alu_out [1:0] $end
    $var wire  1 ( alu_sel $end
    $var wire  1 & clk $end
    $var wire  4 # count [3:0] $end
    $var wire  1 ) mux_sel $end
    $var wire  1 ' rst $end
    $var wire  2 * soc_output [1:0] $end
    $scope module dut $end
     $var wire  1 & clk $end
     $var wire  4 # count [3:0] $end
     $var wire  1 ' rst $end
    $upscope $end
    $scope module sut $end
     $var wire  2 $ in1 [1:0] $end
     $var wire  2 + in2 [1:0] $end
     $var wire  1 ) sel $end
     $var wire  2 * y [1:0] $end
    $upscope $end
    $scope module uut $end
     $var wire  2 $ a [1:0] $end
     $var wire  2 % b [1:0] $end
     $var wire  2 + result [1:0] $end
     $var wire  1 ( sel $end
    $upscope $end
   $upscope $end
  $upscope $end
 $upscope $end
$enddefinitions $end


#0
b0000 #
b00 $
b00 %
0&
0'
0(
0)
b00 *
b00 +
#5
b0001 #
b01 %
1&
b01 *
b01 +
#10
0&
#15
b0010 #
b10 %
1&
b10 *
b10 +
#20
0&
#25
b0011 #
b11 %
1&
b11 *
b11 +
#30
0&
1(
b01 *
b01 +
#35
b0100 #
b01 $
b00 %
1&
#40
0&
#45
b0101 #
b01 %
1&
b00 *
b00 +
#50
0&
#55
b0110 #
b10 %
1&
b11 *
b11 +
#60
0&
#65
b0111 #
b11 %
1&
b10 *
b10 +
#70
0&
#75
b1000 #
b10 $
b00 %
1&
#80
0&
#85
b1001 #
b01 %
1&
b01 *
b01 +
#90
0&
#95
b1010 #
b10 %
1&
b00 *
b00 +
#100
0&
#105
b1011 #
b11 %
1&
b11 *
b11 +
#110
0&
#115
b1100 #
b11 $
b00 %
1&
#120
0&
#125
b1101 #
b01 %
1&
b10 *
b10 +
#130
0&
#135
b1110 #
b10 %
1&
b01 *
b01 +
