Module2_Advanced_RTL_Design_and_CDC_and_RDC_Handling/Multi_Stage_Synchronizer_for_Stable_CDC_using_Verilator/3_stage_synchronizer/sync_stage.v
module sync_stage(input wire clk, input wire async_in,output reg sync_out);
reg ff1,ff2;
always@(posedge clk)begin
	ff1<=async_in;
	ff2<=ff1;
	sync_out<=ff2;
end
endmodule

Module2_Advanced_RTL_Design_and_CDC_and_RDC_Handling/Multi_Stage_Synchronizer_for_Stable_CDC_using_Verilator/3_stage_synchronizer/sync_stage_tb.v
module sync_stage_tb;
reg clk,async_in;
wire sync_out;
sync_stage dut(.clk(clk),.async_in(async_in),.sync_out(sync_out));

always #5 clk<=~clk;
initial begin
	$dumpfile("dump.vcd");
	$dumpvars();
	#5 async_in=1;
	#5 async_in=0;
	#7 async_in=1;
	#50 $finish;
end
endmodule

Module2_Advanced_RTL_Design_and_CDC_and_RDC_Handling/Multi_Stage_Synchronizer_for_Stable_CDC_using_Verilator/3_stage_synchronizer/obj_dir/dump.vcd
$version Generated by VerilatedVcd $end
$timescale 1ps $end

 $scope module TOP $end
  $scope module sync_stage_tb $end
   $var wire  1 ' async_in $end
   $var wire  1 & clk $end
   $var wire  1 # sync_out $end
   $scope module dut $end
    $var wire  1 ' async_in $end
    $var wire  1 & clk $end
    $var wire  1 $ ff1 $end
    $var wire  1 % ff2 $end
    $var wire  1 # sync_out $end
   $upscope $end
  $upscope $end
 $upscope $end
$enddefinitions $end


#0
0#
0$
0%
0&
0'
#5
1$
1&
1'
#10
0&
0'
#15
0$
1%
1&
#17
1'
#20
0&
#25
1#
1$
0%
1&
#30
0&
#35
0#
1%
1&
#40
0&
#45
1#
1&
