Module1_RTL_Design_and_IP_Integration/reset_types/domain_specific_reset/ds.v
module ds(
	input clk1,clk2,rst1,rst2,d1,d2,
	output reg q1,q2);
always @(posedge clk1)begin
	if(rst1)
		q1<=0;
	else
		q1<=d1;
end
always @(posedge clk2)begin
	if(rst2)
		q2<=0;
	else
		q2<=d2;
end
endmodule

Module1_RTL_Design_and_IP_Integration/reset_types/domain_specific_reset/ds_tb.v
module ds_tb;
reg clk1,clk2,rst1,rst2,d1=1,d2=1;
wire q1,q2;
ds dut(.clk1(clk1),.clk2(clk2),.rst1(rst1),.rst2(rst2),.d1(d1),.d2(d2),.q1(q1),.q2(q2));
always #5 clk1<=~clk1;
always #7 clk2<=~clk2;
initial begin
	$dumpfile("ds_dump.vcd");
	$dumpvars();

	#10 rst1=1;#10;rst1=0;
	#10 rst2=0;#10;rst2=1;#50;
	$finish;
end
endmodule

Module1_RTL_Design_and_IP_Integration/reset_types/obj_dir/ds_dump.vcd
$version Generated by VerilatedVcd $end
$timescale 1ps $end

 $scope module TOP $end
  $scope module ds_tb $end
   $var wire  1 # clk1 $end
   $var wire  1 $ clk2 $end
   $var wire  1 ) d1 $end
   $var wire  1 ) d2 $end
   $var wire  1 ' q1 $end
   $var wire  1 ( q2 $end
   $var wire  1 % rst1 $end
   $var wire  1 & rst2 $end
   $scope module dut $end
    $var wire  1 # clk1 $end
    $var wire  1 $ clk2 $end
    $var wire  1 ) d1 $end
    $var wire  1 ) d2 $end
    $var wire  1 ' q1 $end
    $var wire  1 ( q2 $end
    $var wire  1 % rst1 $end
    $var wire  1 & rst2 $end
   $upscope $end
  $upscope $end
 $upscope $end
$enddefinitions $end


#0
0#
0$
0%
0&
0'
0(
1)
#5
1#
1'
#7
1$
1(
#10
0#
1%
#14
0$
#15
1#
0'
#20
0#
0%
#21
1$
#25
1#
1'
#28
0$
#30
0#
#35
1#
1$
#40
0#
1&
#42
0$
#45
1#
#49
1$
0(
