Module1_RTL_Design_and_IP_Integration/mini_soc/soc_err/uart.v
module uart(
	input clk,input rst,input tx_en,input [7:0] tx_data,output reg tx_done);
always @(posedge clk or negedge rst)begin
	if(!rst)
		tx_done<=0;
	else
		if(tx_en)
			tx_done<=1;
		else
			tx_done<=0;
	end
endmodule

Module1_RTL_Design_and_IP_Integration/mini_soc/soc_err/alu.v
module alu(a,b,sel,result);
input [3:0] a,b;
input sel;
output reg [3:0] result;
always@(*)begin
	case(sel)
		1'b0:result=a+b;
		1'b1:result=a-b;
		default:;
	endcase
end
endmodule

Module1_RTL_Design_and_IP_Integration/mini_soc/soc_err/top.v
module top(clk,rst,in1,in2,alu_out,tx_en,tx_done,sel);
input clk,rst,tx_en,sel;
input [3:0] in1,in2;
output [3:0] alu_out;
output tx_done;
wire [3:0] result;
alu uut(.a(in1),.b(in2),.sel(sel),.result(result));
uart dut(.clk(clk),.rst(rst),.tx_en(tx_en),.tx_data({4'b0000,result}),.tx_done(tx_done));
assign alu_out=result;
endmodule

Module1_RTL_Design_and_IP_Integration/mini_soc/soc_err/tb.v
module tb;
 reg clk = 0;
 reg rst = 0;
 reg [3:0] in1, in2;
 reg sel;
 reg tx_en;
 wire tx_done;
 wire [3:0] alu_out;
 always #5 clk <= ~clk;
 top tut (
 .clk(clk),
 .rst(rst),
 .in1(in1),
 .in2(in2),
 .sel(sel),
 .tx_en(tx_en),
 .tx_done(tx_done),
 .alu_out(alu_out)
 );
 initial begin
 $dumpfile("dump.vcd");
 $dumpvars();
 // Apply reset
 #10 rst = 1;
 // Test 1: ADD 4 + 3 = 7, expect UART to transmit 8'b00000111
 in1 = 4; in2 = 3; sel = 0; tx_en = 1;
 #10 tx_en = 0;
 // Test 2: AND 6 - 5 = 1, expect UART to transmit 8'b00000001
 #20 in1 = 6; in2 = 5; sel = 1; tx_en = 1;
 #10 tx_en = 0;
 #40 $finish;
 end
endmodule

Module1_RTL_Design_and_IP_Integration/mini_soc/soc_err/obj_dir/dump.vcd
$version Generated by VerilatedVcd $end
$timescale 1ps $end

 $scope module TOP $end
  $scope module tb $end
   $var wire  4 * alu_out [3:0] $end
   $var wire  1 ( clk $end
   $var wire  4 $ in1 [3:0] $end
   $var wire  4 % in2 [3:0] $end
   $var wire  1 # rst $end
   $var wire  1 & sel $end
   $var wire  1 ) tx_done $end
   $var wire  1 ' tx_en $end
   $scope module tut $end
    $var wire  4 * alu_out [3:0] $end
    $var wire  1 ( clk $end
    $var wire  4 $ in1 [3:0] $end
    $var wire  4 % in2 [3:0] $end
    $var wire  4 * result [3:0] $end
    $var wire  1 # rst $end
    $var wire  1 & sel $end
    $var wire  1 ) tx_done $end
    $var wire  1 ' tx_en $end
    $scope module dut $end
     $var wire  1 ( clk $end
     $var wire  1 # rst $end
     $var wire  8 + tx_data [7:0] $end
     $var wire  1 ) tx_done $end
     $var wire  1 ' tx_en $end
    $upscope $end
    $scope module uut $end
     $var wire  4 $ a [3:0] $end
     $var wire  4 % b [3:0] $end
     $var wire  4 * result [3:0] $end
     $var wire  1 & sel $end
    $upscope $end
   $upscope $end
  $upscope $end
 $upscope $end
$enddefinitions $end


#0
0#
b0000 $
b0000 %
0&
0'
0(
0)
b0000 *
b00000000 +
#5
1(
#10
1#
b0100 $
b0011 %
1'
0(
b0111 *
b00000111 +
#15
1(
1)
#20
0'
0(
#25
1(
0)
#30
0(
#35
1(
#40
b0110 $
b0101 %
1&
1'
0(
b0001 *
b00000001 +
#45
1(
1)
#50
0'
0(
#55
1(
0)
